odoo/addons/fleet_vehicle_purchase/README.rst
odoo/addons/fleet_vehicle_purchase/__init__.py
odoo/addons/fleet_vehicle_purchase/__manifest__.py
odoo/addons/fleet_vehicle_purchase/i18n/es.po
odoo/addons/fleet_vehicle_purchase/i18n/fleet_vehicle_purchase.pot
odoo/addons/fleet_vehicle_purchase/i18n/it.po
odoo/addons/fleet_vehicle_purchase/i18n/pt_BR.po
odoo/addons/fleet_vehicle_purchase/models/__init__.py
odoo/addons/fleet_vehicle_purchase/models/fleet_vehicle.py
odoo/addons/fleet_vehicle_purchase/models/purchase_order.py
odoo/addons/fleet_vehicle_purchase/models/purchase_order_line.py
odoo/addons/fleet_vehicle_purchase/readme/CONTRIBUTORS.md
odoo/addons/fleet_vehicle_purchase/readme/DESCRIPTION.md
odoo/addons/fleet_vehicle_purchase/static/description/icon.png
odoo/addons/fleet_vehicle_purchase/static/description/index.html
odoo/addons/fleet_vehicle_purchase/tests/__init__.py
odoo/addons/fleet_vehicle_purchase/tests/test_purchase.py
odoo/addons/fleet_vehicle_purchase/views/fleet_vehicle.xml
odoo/addons/fleet_vehicle_purchase/views/purchase_order.xml
odoo_addon_fleet_vehicle_purchase-18.0.1.0.0.2.dist-info/METADATA
odoo_addon_fleet_vehicle_purchase-18.0.1.0.0.2.dist-info/WHEEL
odoo_addon_fleet_vehicle_purchase-18.0.1.0.0.2.dist-info/top_level.txt
odoo_addon_fleet_vehicle_purchase-18.0.1.0.0.2.dist-info/RECORD
